light_embed/__init__.py
light_embed/text_embedding.py
light_embed/modules/__init__.py
light_embed/modules/normalize.py
light_embed/modules/ort_base.py
light_embed/modules/ort_text.py
light_embed/modules/pooling.py
light_embed/modules/tokenizer.py
light_embed/utils/__init__.py
light_embed/utils/functions.py
light_embed/utils/model.py
light_embed-1.0.8.dist-info/licenses/LICENSE
light_embed-1.0.8.dist-info/METADATA
light_embed-1.0.8.dist-info/WHEEL
light_embed-1.0.8.dist-info/top_level.txt
light_embed-1.0.8.dist-info/RECORD
