Metadata-Version: 2.4
Name: light-embed
Version: 1.0.8
Summary: Fast and Lightweight Text Embedding
Author-email: Binh Nguyen <binhcode25@gmail.com>
Maintainer-email: Binh Nguyen <binhcode25@gmail.com>
License: MIT
Project-URL: Homepage, https://github.com/nguyenthaibinh/light-embed
Project-URL: Repository, https://github.com/nguyenthaibinh/light-embed
Requires-Python: >=3.11
License-File: LICENSE
Requires-Dist: numpy~=2.3.2
Requires-Dist: huggingface_hub~=0.34.4
Requires-Dist: onnxruntime~=1.22.1
Requires-Dist: tokenizers~=0.22.0
Dynamic: license-file
